CINCLibrary/__init__.py
robotframework_cinc-0.1.4.dist-info/AUTHORS.rst
robotframework_cinc-0.1.4.dist-info/LICENSE
robotframework_cinc-0.1.4.dist-info/METADATA
robotframework_cinc-0.1.4.dist-info/WHEEL
robotframework_cinc-0.1.4.dist-info/top_level.txt
robotframework_cinc-0.1.4.dist-info/RECORD
