Metadata-Version: 2.1
Name: robotframework-cinc
Version: 0.1.4
Summary: Robot Framework Library for integrating cinc auditor tests.
Home-page: https://github.com/tomwerneruk/robotframework-cinc
Author: Tom Werner
Author-email: tom@fluffycloudsandlines.cc
License: MIT license
Keywords: robotframework-cinc
Classifier: Development Status :: 2 - Pre-Alpha
Classifier: Intended Audience :: Developers
Classifier: License :: OSI Approved :: MIT License
Classifier: Natural Language :: English
Classifier: Programming Language :: Python :: 3
Classifier: Programming Language :: Python :: 3.6
Classifier: Programming Language :: Python :: 3.7
Classifier: Programming Language :: Python :: 3.8
Requires-Python: >=3.6
License-File: LICENSE
License-File: AUTHORS.rst
Requires-Dist: robotframework
